{"nodes": [{"id": "kavconsultant_app_dashboard_applications_page_tsx", "label": "page.tsx", "file_type": "code", "source_file": "KavConsultant\\app\\(dashboard)\\applications\\page.tsx", "source_location": "L1"}], "edges": [{"source": "kavconsultant_app_dashboard_applications_page_tsx", "target": "react", "relation": "imports_from", "confidence": "EXTRACTED", "source_file": "KavConsultant\\app\\(dashboard)\\applications\\page.tsx", "source_location": "L1", "weight": 1.0}, {"source": "kavconsultant_app_dashboard_applications_page_tsx", "target": "dynamic", "relation": "imports_from", "confidence": "EXTRACTED", "source_file": "KavConsultant\\app\\(dashboard)\\applications\\page.tsx", "source_location": "L2", "weight": 1.0}, {"source": "kavconsultant_app_dashboard_applications_page_tsx", "target": "kanban_skeleton", "relation": "imports_from", "confidence": "EXTRACTED", "source_file": "KavConsultant\\app\\(dashboard)\\applications\\page.tsx", "source_location": "L3", "weight": 1.0}], "raw_calls": []}